[
    {
        "id": 16,
        "title": "Apple",
        "description": "Fresh and crisp apples, perfect for snacking or incorporating into various recipes.",
        "category": "groceries",
        "price": 1.99,
        "discountPercentage": 1.97,
        "rating": 2.96,
        "stock": 9,
        "tags": [
            "fruits"
        ],
        "sku": "QTROUV79",
        "weight": 8,
        "dimensions": {
            "width": 8.29,
            "height": 5.58,
            "depth": 12.41
        },
        "warrantyInformation": "2 year warranty",
        "shippingInformation": "Ships in 2 weeks",
        "availabilityStatus": "In Stock",
        "reviews": [
            {
                "rating": 4,
                "comment": "Great product!",
                "date": "2024-05-23T08:56:21.620Z",
                "reviewerName": "Logan Lee",
                "reviewerEmail": "logan.lee@x.dummyjson.com"
            },
            {
                "rating": 4,
                "comment": "Great product!",
                "date": "2024-05-23T08:56:21.620Z",
                "reviewerName": "Elena Long",
                "reviewerEmail": "elena.long@x.dummyjson.com"
            },
            {
                "rating": 1,
                "comment": "Not as described!",
                "date": "2024-05-23T08:56:21.620Z",
                "reviewerName": "Grayson Coleman",
                "reviewerEmail": "grayson.coleman@x.dummyjson.com"
            }
        ],
        "returnPolicy": "60 days return policy",
        "minimumOrderQuantity": 44,
        "meta": {
            "createdAt": "2024-05-23T08:56:21.620Z",
            "updatedAt": "2024-05-23T08:56:21.620Z",
            "barcode": "2517819903837",
            "qrCode": "https://assets.dummyjson.com/public/qr-code.png"
        },
        "images": [
            "https://cdn.dummyjson.com/products/images/groceries/Apple/1.png"
        ],
        "thumbnail": "https://cdn.dummyjson.com/products/images/groceries/Apple/thumbnail.png"
    },
    {
        "id": 17,
        "title": "Beef Steak",
        "description": "High-quality beef steak, great for grilling or cooking to your preferred level of doneness.",
        "category": "groceries",
        "price": 12.99,
        "discountPercentage": 17.99,
        "rating": 2.83,
        "stock": 96,
        "tags": [
            "meat"
        ],
        "sku": "BWWA2MSO",
        "weight": 9,
        "dimensions": {
            "width": 23.35,
            "height": 13.48,
            "depth": 26.4
        },
        "warrantyInformation": "1 month warranty",
        "shippingInformation": "Ships overnight",
        "availabilityStatus": "In Stock",
        "reviews": [
            {
                "rating": 4,
                "comment": "Very pleased!",
                "date": "2024-05-23T08:56:21.620Z",
                "reviewerName": "Ethan Martinez",
                "reviewerEmail": "ethan.martinez@x.dummyjson.com"
            },
            {
                "rating": 3,
                "comment": "Disappointing product!",
                "date": "2024-05-23T08:56:21.620Z",
                "reviewerName": "Owen Fisher",
                "reviewerEmail": "owen.fisher@x.dummyjson.com"
            },
            {
                "rating": 4,
                "comment": "Very happy with my purchase!",
                "date": "2024-05-23T08:56:21.620Z",
                "reviewerName": "Scarlett Wright",
                "reviewerEmail": "scarlett.wright@x.dummyjson.com"
            }
        ],
        "returnPolicy": "90 days return policy",
        "minimumOrderQuantity": 21,
        "meta": {
            "createdAt": "2024-05-23T08:56:21.620Z",
            "updatedAt": "2024-05-23T08:56:21.620Z",
            "barcode": "8335515097879",
            "qrCode": "https://assets.dummyjson.com/public/qr-code.png"
        },
        "images": [
            "https://cdn.dummyjson.com/products/images/groceries/Beef%20Steak/1.png"
        ],
        "thumbnail": "https://cdn.dummyjson.com/products/images/groceries/Beef%20Steak/thumbnail.png"
    },
    {
        "id": 18,
        "title": "Cat Food",
        "description": "Nutritious cat food formulated to meet the dietary needs of your feline friend.",
        "category": "groceries",
        "price": 8.99,
        "discountPercentage": 9.57,
        "rating": 2.88,
        "stock": 13,
        "tags": [
            "pet supplies",
            "cat food"
        ],
        "sku": "C3F8QN6O",
        "weight": 9,
        "dimensions": {
            "width": 15.4,
            "height": 13.97,
            "depth": 25.13
        },
        "warrantyInformation": "3 months warranty",
        "shippingInformation": "Ships in 1-2 business days",
        "availabilityStatus": "In Stock",
        "reviews": [
            {
                "rating": 5,
                "comment": "Very pleased!",
                "date": "2024-05-23T08:56:21.620Z",
                "reviewerName": "Mateo Bennett",
                "reviewerEmail": "mateo.bennett@x.dummyjson.com"
            },
            {
                "rating": 5,
                "comment": "Very pleased!",
                "date": "2024-05-23T08:56:21.620Z",
                "reviewerName": "Aurora Barnes",
                "reviewerEmail": "aurora.barnes@x.dummyjson.com"
            },
            {
                "rating": 5,
                "comment": "Great value for money!",
                "date": "2024-05-23T08:56:21.620Z",
                "reviewerName": "Ellie Stewart",
                "reviewerEmail": "ellie.stewart@x.dummyjson.com"
            }
        ],
        "returnPolicy": "7 days return policy",
        "minimumOrderQuantity": 48,
        "meta": {
            "createdAt": "2024-05-23T08:56:21.620Z",
            "updatedAt": "2024-05-23T08:56:21.620Z",
            "barcode": "5503491330693",
            "qrCode": "https://assets.dummyjson.com/public/qr-code.png"
        },
        "images": [
            "https://cdn.dummyjson.com/products/images/groceries/Cat%20Food/1.png"
        ],
        "thumbnail": "https://cdn.dummyjson.com/products/images/groceries/Cat%20Food/thumbnail.png"
    },
    {
        "id": 19,
        "title": "Chicken Meat",
        "description": "Fresh and tender chicken meat, suitable for various culinary preparations.",
        "category": "groceries",
        "price": 9.99,
        "discountPercentage": 10.46,
        "rating": 4.61,
        "stock": 69,
        "tags": [
            "meat"
        ],
        "sku": "G5YEHW7B",
        "weight": 7,
        "dimensions": {
            "width": 15.96,
            "height": 29.24,
            "depth": 26.25
        },
        "warrantyInformation": "Lifetime warranty",
        "shippingInformation": "Ships in 1 month",
        "availabilityStatus": "In Stock",
        "reviews": [
            {
                "rating": 5,
                "comment": "Very satisfied!",
                "date": "2024-05-23T08:56:21.620Z",
                "reviewerName": "Sophia Jones",
                "reviewerEmail": "sophia.jones@x.dummyjson.com"
            },
            {
                "rating": 5,
                "comment": "Great value for money!",
                "date": "2024-05-23T08:56:21.620Z",
                "reviewerName": "Maya Reed",
                "reviewerEmail": "maya.reed@x.dummyjson.com"
            },
            {
                "rating": 4,
                "comment": "Highly recommended!",
                "date": "2024-05-23T08:56:21.620Z",
                "reviewerName": "Harper Turner",
                "reviewerEmail": "harper.turner@x.dummyjson.com"
            }
        ],
        "returnPolicy": "7 days return policy",
        "minimumOrderQuantity": 46,
        "meta": {
            "createdAt": "2024-05-23T08:56:21.620Z",
            "updatedAt": "2024-05-23T08:56:21.620Z",
            "barcode": "0966223559510",
            "qrCode": "https://assets.dummyjson.com/public/qr-code.png"
        },
        "images": [
            "https://cdn.dummyjson.com/products/images/groceries/Chicken%20Meat/1.png",
            "https://cdn.dummyjson.com/products/images/groceries/Chicken%20Meat/2.png"
        ],
        "thumbnail": "https://cdn.dummyjson.com/products/images/groceries/Chicken%20Meat/thumbnail.png"
    },
    {
        "id": 20,
        "title": "Cooking Oil",
        "description": "Versatile cooking oil suitable for frying, sautéing, and various culinary applications.",
        "category": "groceries",
        "price": 4.99,
        "discountPercentage": 18.89,
        "rating": 4.01,
        "stock": 22,
        "tags": [
            "cooking essentials"
        ],
        "sku": "Q6ZP1UY8",
        "weight": 8,
        "dimensions": {
            "width": 8.18,
            "height": 27.45,
            "depth": 27.88
        },
        "warrantyInformation": "Lifetime warranty",
        "shippingInformation": "Ships in 1 month",
        "availabilityStatus": "In Stock",
        "reviews": [
            {
                "rating": 5,
                "comment": "Would buy again!",
                "date": "2024-05-23T08:56:21.620Z",
                "reviewerName": "Mason Parker",
                "reviewerEmail": "mason.parker@x.dummyjson.com"
            },
            {
                "rating": 3,
                "comment": "Poor quality!",
                "date": "2024-05-23T08:56:21.620Z",
                "reviewerName": "Jonathan Pierce",
                "reviewerEmail": "jonathan.pierce@x.dummyjson.com"
            },
            {
                "rating": 5,
                "comment": "Would buy again!",
                "date": "2024-05-23T08:56:21.620Z",
                "reviewerName": "Alexander Hernandez",
                "reviewerEmail": "alexander.hernandez@x.dummyjson.com"
            }
        ],
        "returnPolicy": "60 days return policy",
        "minimumOrderQuantity": 2,
        "meta": {
            "createdAt": "2024-05-23T08:56:21.620Z",
            "updatedAt": "2024-05-23T08:56:21.620Z",
            "barcode": "6707669443381",
            "qrCode": "https://assets.dummyjson.com/public/qr-code.png"
        },
        "images": [
            "https://cdn.dummyjson.com/products/images/groceries/Cooking%20Oil/1.png"
        ],
        "thumbnail": "https://cdn.dummyjson.com/products/images/groceries/Cooking%20Oil/thumbnail.png"
    }
]